HakObserverpy/HakObserverpy.py
HakObserverpy/__init__.py
HakObserverpy-2.2.1.dist-info/METADATA
HakObserverpy-2.2.1.dist-info/WHEEL
HakObserverpy-2.2.1.dist-info/top_level.txt
HakObserverpy-2.2.1.dist-info/RECORD
