Metadata-Version: 2.1
Name: HakObserverpy
Version: 2.2.1
Summary: A package connect endpoints to the Hakware Application
Author: Jacob O'Brien
Classifier: Programming Language :: Python :: 3
Classifier: License :: OSI Approved :: MIT License
Classifier: Operating System :: OS Independent
Requires-Python: >=3.6
Requires-Dist: requests
Requires-Dist: psutil
Requires-Dist: lxml[html_clean]
Requires-Dist: requests-html
Requires-Dist: pywin32
